fontRepertoire/__init__.py
fontRepertoire/base.py
fontRepertoire/characterSet.py
fontRepertoire/codepointToGlyphMap.py
fontRepertoire/glyphRepertoire.py
fontRepertoire-0.1.8.dist-info/LICENSE
fontRepertoire-0.1.8.dist-info/METADATA
fontRepertoire-0.1.8.dist-info/WHEEL
fontRepertoire-0.1.8.dist-info/top_level.txt
fontRepertoire-0.1.8.dist-info/RECORD
