Metadata-Version: 2.1
Name: fontRepertoire
Version: 0.1.8
Summary: Basic classes to represent character set and glyph repertoire.
Home-page: https://gitlab.com/fontstuff/fontRepertoire
Author: Andreas Eigendorf
License: MIT
Project-URL: Source, https://gitlab.com/fontstuff/fontRepertoire
Project-URL: Documentation, https://fontstuff.gitlab.io/fontRepertoire
Project-URL: Tracker, https://gitlab.com/fontstuff/fontRepertoire/-/issues
Keywords: font
Platform: Any
Classifier: Development Status :: 3 - Alpha
Classifier: License :: OSI Approved :: MIT License
Classifier: Operating System :: OS Independent
Classifier: Programming Language :: Python :: 3
Classifier: Programming Language :: Python :: 3.8
Classifier: Programming Language :: Python :: 3.9
Classifier: Programming Language :: Python :: 3.10
Classifier: Programming Language :: Python :: 3.11
Classifier: Programming Language :: Python :: 3.12
Classifier: Intended Audience :: Developers
Classifier: Topic :: Multimedia :: Graphics
Classifier: Topic :: Software Development :: Libraries
Requires-Python: >=3.8
License-File: LICENSE
Requires-Dist: fonttools[ufo,unicode,woff] >=4.51
Requires-Dist: glyphsLib >=6.7.1
Requires-Dist: unicodedata2 >=15.1
Requires-Dist: typing-extensions >=4.8 ; python_version < "3.11"
